turnwise/__init__.py
turnwise/client.py
turnwise/api/__init__.py
turnwise/api/client.py
turnwise/evaluation/__init__.py
turnwise/evaluation/evaluation_agent.py
turnwise/evaluation/goal_agent.py
turnwise/evaluation/orchestrator.py
turnwise/evaluation/output_models.py
turnwise/llm/__init__.py
turnwise/llm/provider.py
turnwise/metrics/__init__.py
turnwise/metrics/default_metrics.py
turnwise/models/__init__.py
turnwise/models/conversation.py
turnwise/models/enums.py
turnwise/models/evaluation.py
turnwise/prompts/__init__.py
turnwise/utils/__init__.py
turnwise_sdk-0.1.0.dist-info/METADATA
turnwise_sdk-0.1.0.dist-info/WHEEL
turnwise_sdk-0.1.0.dist-info/licenses/LICENSE
turnwise_sdk-0.1.0.dist-info/RECORD
