Metadata-Version: 2.4
Name: turnwise-sdk
Version: 0.1.0
Summary: TurnWise Python SDK - Run LLM conversation evaluations locally
Project-URL: Homepage, https://turnwise.io
Project-URL: Documentation, https://docs.turnwise.io/sdk
Project-URL: Repository, https://github.com/turnwise/turnwise-python
Author-email: TurnWise <support@turnwise.io>
License: MIT
License-File: LICENSE
Keywords: ai,conversation,evaluation,llm,turnwise
Classifier: Development Status :: 3 - Alpha
Classifier: Intended Audience :: Developers
Classifier: License :: OSI Approved :: MIT License
Classifier: Programming Language :: Python :: 3.10
Classifier: Programming Language :: Python :: 3.11
Classifier: Programming Language :: Python :: 3.12
Classifier: Topic :: Scientific/Engineering :: Artificial Intelligence
Requires-Python: >=3.10
Requires-Dist: httpx>=0.25.0
Requires-Dist: langchain-openai>=0.1.0
Requires-Dist: langchain>=0.2.0
Requires-Dist: pydantic>=2.5.0
Requires-Dist: tenacity>=8.2.0
Requires-Dist: tiktoken>=0.5.0
Requires-Dist: tqdm>=4.65.0
Provides-Extra: dev
Requires-Dist: black>=23.11.0; extra == 'dev'
Requires-Dist: mypy>=1.7.0; extra == 'dev'
Requires-Dist: pytest-asyncio>=0.21.0; extra == 'dev'
Requires-Dist: pytest>=7.4.0; extra == 'dev'
Requires-Dist: ruff>=0.1.6; extra == 'dev'
